{
  "pixelmonName": "Braixen",
  "pokemon": "Braixen",
  "form": 0,
  "stats": {
    "HP": 59,
    "Attack": 59,
    "Defence": 58,
    "Speed": 73,
    "SpecialAttack": 90,
    "SpecialDefence": 70
  },
  "catchRate": 45,
  "malePercent": 87,
  "spawnLevel": 16,
  "spawnLevelRange": 20,
  "baseExp": 143,
  "baseFriendship": 0,
  "types": [
    "Fire"
  ],
  "height": 1.0,
  "isRideable": false,
  "canFly": false,
  "canSurf": false,
  "preEvolutions": [
    "Fennekin"
  ],
  "experienceGroup": "MediumSlow",
  "aggression": {
    "timid": 80,
    "passive": 0,
    "aggressive": 20
  },
  "spawnLocations": [
    "Land"
  ],
  "evYields": {
    "SpecialAttack": 2
  },
  "weight": 14.5,
  "bounding_box": {
    "width": 1.0,
    "height": 1.0,
    "eye_height": 0.7
  },
  "evolutions": [
    {
      "level": 36,
      "to": {
        "name": "Delphox"
      },
      "conditions": [],
      "evoType": "leveling",
      "moves": [
        "Mystical Fire"
      ]
    }
  ],
  "abilities": [
    "Blaze",
    null,
    "Magician"
  ],
  "eggGroups": [
    "Field"
  ],
  "eggCycles": 21,
  "levelUpMoves": {
    "0": [
      "Ember",
      "Scratch",
      "Tail Whip"
    ],
    "5": [
      "Ember"
    ],
    "11": [
      "Howl"
    ],
    "14": [
      "Flame Charge"
    ],
    "18": [
      "Psybeam"
    ],
    "22": [
      "Fire Spin"
    ],
    "28": [
      "Lucky Chant"
    ],
    "31": [
      "Light Screen"
    ],
    "36": [
      "Psyshock"
    ],
    "41": [
      "Flamethrower"
    ],
    "45": [
      "Will-O-Wisp"
    ],
    "49": [
      "Psychic"
    ],
    "52": [
      "Sunny Day"
    ],
    "56": [
      "Magic Room"
    ],
    "59": [
      "Fire Blast"
    ]
  },
  "tutorMoves": [
    "Ally Switch",
    "Covet",
    "Fire Pledge",
    "Fire Punch",
    "Foul Play",
    "Heat Wave",
    "Iron Tail",
    "Laser Focus",
    "Low Kick",
    "Magic Coat",
    "Magic Room",
    "Recycle",
    "Shock Wave",
    "Skill Swap",
    "Snatch",
    "Snore",
    "Telekinesis",
    "Thunder Punch",
    "Trick",
    "Wonder Room",
    "Zen Headbutt"
  ],
  "eggMoves": [
    "Heat Wave",
    "Hypnosis",
    "Magic Coat",
    "Psychic Terrain",
    "Wish"
  ],
  "transferMoves": [
    "Cut",
    "Incinerate",
    "Power-Up Punch",
    "Secret Power"
  ],
  "hmMoves": [],
  "tmMoves7": [
    "Work Up",
    "Psyshock",
    "Toxic",
    "Hidden Power",
    "Sunny Day",
    "Light Screen",
    "Protect",
    "Rain Dance",
    "Safeguard",
    "Frustration",
    "Solar Beam",
    "Return",
    "Psychic",
    "Double Team",
    "Flamethrower",
    "Fire Blast",
    "Facade",
    "Flame Charge",
    "Rest",
    "Attract",
    "Thief",
    "Round",
    "Echoed Voice",
    "Overheat",
    "Will-O-Wisp",
    "Embargo",
    "Psych Up",
    "Dream Eater",
    "Grass Knot",
    "Swagger",
    "Sleep Talk",
    "Substitute",
    "Confide"
  ],
  "tmMoves6": [
    "Psyshock",
    "Toxic",
    "Hidden Power",
    "Sunny Day",
    "Light Screen",
    "Protect",
    "Rain Dance",
    "Safeguard",
    "Frustration",
    "Solar Beam",
    "Return",
    "Psychic",
    "Double Team",
    "Flamethrower",
    "Fire Blast",
    "Facade",
    "Flame Charge",
    "Rest",
    "Attract",
    "Thief",
    "Round",
    "Echoed Voice",
    "Overheat",
    "Incinerate",
    "Will-O-Wisp",
    "Embargo",
    "Psych Up",
    "Dream Eater",
    "Grass Knot",
    "Swagger",
    "Sleep Talk",
    "Substitute",
    "Secret Power",
    "Power-Up Punch",
    "Confide"
  ],
  "forms": {}
}