{
  "pixelmonName": "Comfey",
  "pokemon": "Comfey",
  "form": -1,
  "stats": {
    "HP": 51,
    "Attack": 52,
    "Defence": 90,
    "Speed": 100,
    "SpecialAttack": 82,
    "SpecialDefence": 110
  },
  "catchRate": 60,
  "malePercent": 25,
  "spawnLevel": 20,
  "spawnLevelRange": 40,
  "baseExp": 170,
  "baseFriendship": 70,
  "types": [
    "Fairy"
  ],
  "height": 0.5,
  "isRideable": false,
  "canFly": false,
  "canSurf": false,
  "preEvolutions": [],
  "experienceGroup": "Fast",
  "aggression": {
    "timid": 80,
    "passive": 0,
    "aggressive": 20
  },
  "spawnLocations": [],
  "evYields": {
    "SpecialDefence": 2
  },
  "weight": 0.3,
  "bounding_box": {
    "width": 0.4,
    "height": 1.4,
    "eye_height": 1.1
  },
  "evolutions": [],
  "abilities": [
    "FlowerVeil",
    "Triage",
    "NaturalCure"
  ],
  "eggGroups": [
    "Grass"
  ],
  "eggCycles": 20,
  "levelUpMoves": {
    "0": [
      "Growth",
      "Wrap"
    ],
    "3": [
      "Vine Whip"
    ],
    "6": [
      "Helping Hand"
    ],
    "9": [
      "Draining Kiss"
    ],
    "12": [
      "Flower Shield"
    ],
    "15": [
      "Magical Leaf"
    ],
    "18": [
      "Synthesis"
    ],
    "21": [
      "Leech Seed"
    ],
    "24": [
      "Grass Knot"
    ],
    "27": [
      "Sweet Kiss"
    ],
    "30": [
      "Floral Healing"
    ],
    "33": [
      "Petal Blizzard"
    ],
    "36": [
      "Aromatherapy"
    ],
    "39": [
      "Play Rough"
    ],
    "42": [
      "Sweet Scent"
    ],
    "45": [
      "Petal Dance"
    ],
    "48": [
      "Grassy Terrain"
    ]
  },
  "tutorMoves": [
    "Grassy Glide"
  ],
  "eggMoves": [
    "After You",
    "Leaf Tornado",
    "Worry Seed"
  ],
  "transferMoves": [
    "Bind",
    "Celebrate",
    "Confide",
    "Covet",
    "Defog",
    "Double Team",
    "Echoed Voice",
    "Frustration",
    "Heal Bell",
    "Hidden Power",
    "Lucky Chant",
    "Magic Coat",
    "Natural Gift",
    "Nature Power",
    "Pain Split",
    "Psych Up",
    "Return",
    "Role Play",
    "Swagger",
    "Tailwind",
    "Telekinesis",
    "Toxic"
  ],
  "hmMoves": [],
  "trMoves": [
    "Amnesia",
    "Substitute",
    "Endure",
    "Sleep Talk",
    "Encore",
    "Taunt",
    "Trick",
    "Calm Mind",
    "Seed Bomb",
    "Energy Ball",
    "Grass Knot",
    "Stored Power",
    "Ally Switch",
    "Play Rough",
    "Dazzling Gleam",
    "Pollen Puff"
  ],
  "tmMoves8": [
    "Hyper Beam",
    "Magical Leaf",
    "Solar Beam",
    "Light Screen",
    "Safeguard",
    "Rest",
    "Thief",
    "Snore",
    "Protect",
    "Giga Drain",
    "Charm",
    "Attract",
    "Sunny Day",
    "Facade",
    "Helping Hand",
    "Bullet Seed",
    "U-turn",
    "Fling",
    "Trick Room",
    "Round",
    "Acrobatics",
    "Draining Kiss",
    "Grassy Terrain"
  ],
  "tmMoves7": [
    "Calm Mind",
    "Toxic",
    "Hidden Power",
    "Sunny Day",
    "Taunt",
    "Hyper Beam",
    "Light Screen",
    "Protect",
    "Safeguard",
    "Frustration",
    "Solar Beam",
    "Return",
    "Double Team",
    "Facade",
    "Rest",
    "Attract",
    "Thief",
    "Round",
    "Echoed Voice",
    "Energy Ball",
    "Fling",
    "Acrobatics",
    "Psych Up",
    "Grass Knot",
    "Swagger",
    "Sleep Talk",
    "U-turn",
    "Substitute",
    "Trick Room",
    "Nature Power",
    "Dazzling Gleam",
    "Confide"
  ],
  "forms": {}
}